{"string":" ambeepollenAPIgrass_pollen == ambeepollenAPIgrass_pollen && ambeepollenAPIweed_pollen == ambeepollenAPIweed_pollen && ambeepollenAPItree_pollen == ambeepollenAPItree_pollen && waterwaporAPIwater_vapor == waterwaporAPIwater_vapor ","name":"provapollenvapor","condition":{"1":{"0":"ambeepollenAPIgrass_pollen","1":"==","2":"ambeepollenAPIgrass_pollen","3":"&&"},"2":{"0":"ambeepollenAPIweed_pollen","1":"==","2":"ambeepollenAPIweed_pollen","3":"&&"},"3":{"0":"ambeepollenAPItree_pollen","1":"==","2":"ambeepollenAPItree_pollen","3":"&&"},"4":{"0":"waterwaporAPIwater_vapor","1":"==","2":"waterwaporAPIwater_vapor","3":""}},"then":{"action":"print_to_Lcd","param":"ambeepollenAPIgrass_pollen"},"else":{"action":"Action","param":"Parameters"}}